goes_ortho_test/__init__.py
goes_ortho_test/common.py
goes_ortho_test/goes_ortho_test.py
goes_ortho_test-0.0.2.dist-info/LICENSE
goes_ortho_test-0.0.2.dist-info/METADATA
goes_ortho_test-0.0.2.dist-info/WHEEL
goes_ortho_test-0.0.2.dist-info/entry_points.txt
goes_ortho_test-0.0.2.dist-info/top_level.txt
goes_ortho_test-0.0.2.dist-info/RECORD
